zipp/__init__.py
zipp/glob.py
zipp/compat/__init__.py
zipp/compat/overlay.py
zipp/compat/py310.py
zipp-3.20.1.dist-info/LICENSE
zipp-3.20.1.dist-info/METADATA
zipp-3.20.1.dist-info/WHEEL
zipp-3.20.1.dist-info/top_level.txt
zipp-3.20.1.dist-info/RECORD
