Metadata-Version: 2.1
Name: zipp
Version: 3.20.1
Summary: Backport of pathlib-compatible object wrapper for zip files
Author-email: "Jason R. Coombs" <jaraco@jaraco.com>
Project-URL: Source, https://github.com/jaraco/zipp
Classifier: Development Status :: 5 - Production/Stable
Classifier: Intended Audience :: Developers
Classifier: License :: OSI Approved :: MIT License
Classifier: Programming Language :: Python :: 3
Classifier: Programming Language :: Python :: 3 :: Only
Requires-Python: >=3.8
License-File: LICENSE
Provides-Extra: test
Requires-Dist: pytest!=8.1.*,>=6; extra == "test"
Requires-Dist: jaraco.itertools; extra == "test"
Requires-Dist: jaraco.functools; extra == "test"
Requires-Dist: more_itertools; extra == "test"
Requires-Dist: big-O; extra == "test"
Requires-Dist: pytest-ignore-flaky; extra == "test"
Requires-Dist: jaraco.test; extra == "test"
Requires-Dist: importlib_resources; python_version < "3.9" and extra == "test"
Provides-Extra: doc
Requires-Dist: sphinx>=3.5; extra == "doc"
Requires-Dist: jaraco.packaging>=9.3; extra == "doc"
Requires-Dist: rst.linker>=1.9; extra == "doc"
Requires-Dist: furo; extra == "doc"
Requires-Dist: sphinx-lint; extra == "doc"
Requires-Dist: jaraco.tidelift>=1.4; extra == "doc"
Provides-Extra: check
Requires-Dist: pytest-checkdocs>=2.4; extra == "check"
Requires-Dist: pytest-ruff>=0.2.1; sys_platform != "cygwin" and extra == "check"
Provides-Extra: cover
Requires-Dist: pytest-cov; extra == "cover"
Provides-Extra: enabler
Requires-Dist: pytest-enabler>=2.2; extra == "enabler"
Provides-Extra: type
Requires-Dist: pytest-mypy; extra == "type"
